latex_ji18n/__init__.py
latex_ji18n/__main__.py
latex_ji18n/config.py
latex_ji18n/context.py
latex_ji18n/environment.py
latex_ji18n/executable.py
latex_ji18n/filters.py
latex_ji18n/io.py
latex_ji18n/render.py
latex_ji18n/biber/__init__.py
latex_ji18n/commands/__init__.py
latex_ji18n/commands/build.py
latex_ji18n-0.0.6.dist-info/LICENSE
latex_ji18n-0.0.6.dist-info/METADATA
latex_ji18n-0.0.6.dist-info/WHEEL
latex_ji18n-0.0.6.dist-info/entry_points.txt
latex_ji18n-0.0.6.dist-info/top_level.txt
latex_ji18n-0.0.6.dist-info/RECORD
