Metadata-Version: 2.1
Name: latex-ji18n
Version: 0.0.6
Summary: LaTeX Jinja2 i18n utilities.
Home-page: https://github.com/mondeja/latex-ji18n
Author: Álvaro Mondéjar Rubio
Author-email: mondejar1994@gmail.com
License: BSD License
Project-URL: GitHub Project, https://github.com/mondeja/latex-ji18n
Project-URL: Issue Tracker, https://github.com/mondeja/latex-ji18n/issues
Platform: UNKNOWN
Classifier: License :: OSI Approved :: BSD License
Classifier: Operating System :: OS Independent
Classifier: Development Status :: 4 - Beta
Classifier: Programming Language :: Python
Classifier: Programming Language :: Python :: 3.6
Classifier: Programming Language :: Python :: 3.7
Classifier: Programming Language :: Python :: 3.8
Classifier: Programming Language :: Python :: 3.9
Classifier: Programming Language :: Python :: Implementation :: CPython
Classifier: Programming Language :: Python :: Implementation :: PyPy
Classifier: Topic :: Software Development :: Internationalization
Classifier: Topic :: Text Processing
Classifier: Topic :: Text Processing :: Markup :: LaTeX
Requires-Python: >=3
Requires-Dist: jinja2 (>=2.11.2)
Requires-Dist: inflection (>=0.5.1)
Requires-Dist: ruamel.yaml (>=0.16.10)
Requires-Dist: click (>=7.1.2)
Requires-Dist: bibtexparser (>=1.2.0)
Provides-Extra: dev
Requires-Dist: twine (==3.2.0) ; extra == 'dev'
Requires-Dist: bump2version (==1.0.1) ; extra == 'dev'
Requires-Dist: pre-commit (==2.9.2) ; extra == 'dev'
Provides-Extra: lint
Requires-Dist: flake8 (==3.8.4) ; extra == 'lint'
Requires-Dist: flake8-print (==3.1.4) ; extra == 'lint'
Requires-Dist: flake8-implicit-str-concat (==0.2.0) ; extra == 'lint'
Requires-Dist: isort (==5.6.4) ; extra == 'lint'
Requires-Dist: yamllint (==1.25.0) ; extra == 'lint'
